signpost_debug_radio/__init__.py
signpost_debug_radio/_version.py
signpost_debug_radio/main.py
signpost_debug_radio-0.2.1.dist-info/DESCRIPTION.rst
signpost_debug_radio-0.2.1.dist-info/METADATA
signpost_debug_radio-0.2.1.dist-info/RECORD
signpost_debug_radio-0.2.1.dist-info/WHEEL
signpost_debug_radio-0.2.1.dist-info/entry_points.txt
signpost_debug_radio-0.2.1.dist-info/metadata.json
signpost_debug_radio-0.2.1.dist-info/top_level.txt
