Metadata-Version: 1.0
Name: signpost-debug-radio
Version: 0.2.1
Summary: Signpost Debug Radio Interface
Home-page: https://github.com/lab11/signpost
Author: Brad Campbell
Author-email: bradjc@umich.edu
License: UNKNOWN
Platform: UNKNOWN
